odoo/addons/stock_picking_cancel_reason/README.rst
odoo/addons/stock_picking_cancel_reason/__init__.py
odoo/addons/stock_picking_cancel_reason/__manifest__.py
odoo/addons/stock_picking_cancel_reason/data/stock_picking_cancel_reason.xml
odoo/addons/stock_picking_cancel_reason/i18n/pt_BR.po
odoo/addons/stock_picking_cancel_reason/i18n/stock_picking_cancel_reason.pot
odoo/addons/stock_picking_cancel_reason/model/__init__.py
odoo/addons/stock_picking_cancel_reason/model/stock_picking.py
odoo/addons/stock_picking_cancel_reason/readme/CONFIGURE.rst
odoo/addons/stock_picking_cancel_reason/readme/CONTRIBUTORS.rst
odoo/addons/stock_picking_cancel_reason/readme/CREDITS.rst
odoo/addons/stock_picking_cancel_reason/readme/DESCRIPTION.rst
odoo/addons/stock_picking_cancel_reason/security/ir.model.access.csv
odoo/addons/stock_picking_cancel_reason/static/description/icon.png
odoo/addons/stock_picking_cancel_reason/static/description/index.html
odoo/addons/stock_picking_cancel_reason/tests/__init__.py
odoo/addons/stock_picking_cancel_reason/tests/test_stock_picking_cancel_reason.py
odoo/addons/stock_picking_cancel_reason/views/stock_picking_views.xml
odoo/addons/stock_picking_cancel_reason/wizard/__init__.py
odoo/addons/stock_picking_cancel_reason/wizard/stock_picking_cancel_reason.py
odoo/addons/stock_picking_cancel_reason/wizard/stock_picking_cancel_reason_view.xml
odoo14_addon_stock_picking_cancel_reason-14.0.1.0.1.dist-info/METADATA
odoo14_addon_stock_picking_cancel_reason-14.0.1.0.1.dist-info/WHEEL
odoo14_addon_stock_picking_cancel_reason-14.0.1.0.1.dist-info/top_level.txt
odoo14_addon_stock_picking_cancel_reason-14.0.1.0.1.dist-info/RECORD
